[
  {
    "id": "id-1",
    "name": "Блендер Scarlet",
    "description": "",
    "oldPrice": "1.920",
    "price": "1.760",
    "novelty": false,
    "promotion": "20",
    "picture": "images/blender.png",
    "picture2x": "images/blender-2x.png"
  },
  {
    "id": "id-2",
    "name": "Чайник Scarlet",
    "description": "",
    "oldPrice": "",
    "price": "1.590",
    "novelty": true,
    "promotion": "",
    "picture": "images/kettle-scarlett.png",
    "picture2x": "images/kettle-scarlett-2x.png"
  },
  {
    "id": "id-3",
    "name": "Тостер Scarlet",
    "description": "",
    "oldPrice": "",
    "price": "1.120",
    "novelty": false,
    "promotion": "",
    "picture": "images/toaster.png",
    "picture2x": "images/toaster-2x.png"
  },
  {
    "id": "id-4",
    "name": "Міксер Scarlet",
    "description": "",
    "oldPrice": "",
    "price": "1.860",
    "novelty": false,
    "promotion": "",
    "picture": "images/mixer.png",
    "picture2x": "images/mixer-2x.png"
  },
  {
    "id": "id-5",
    "name": "Cоковижималка Scarlet",
    "description": "",
    "oldPrice": "",
    "price": "2.140",
    "novelty": false,
    "promotion": "",
    "picture": "images/juicer.png",
    "picture2x": "images/juicer-2x.png"
  },
  {
    "id": "id-6",
    "name": "Кавомолка Scarlet",
    "description": "",
    "oldPrice": "",
    "price": "1.120",
    "novelty": false,
    "promotion": "",
    "picture": "images/coffee-grinder.png",
    "picture2x": "images/coffee-grinder-2x.png"
  },
  {
    "id": "id-7",
    "name": "Кавомашина Scarlet",
    "description": "",
    "oldPrice": "5.920",
    "price": "4.890",
    "novelty": false,
    "promotion": "20",
    "picture": "images/coffee-machine-scarlett.png",
    "picture2x": "images/coffee-machine-scarlett-2x.png"
  },
  {
    "id": "id-8",
    "name": "М'ясорубка Scarlet",
    "description": "",
    "oldPrice": "",
    "price": "2.360",
    "novelty": false,
    "promotion": "",
    "picture": "images/meat-grinder.png",
    "picture2x": "images/meat-grinder-2x.png"
  }
]
